deepnumpy/__init__.py
deepnumpy-0.1.0.dist-info/METADATA
deepnumpy-0.1.0.dist-info/RECORD
deepnumpy-0.1.0.dist-info/WHEEL
deepnumpy-0.1.0.dist-info/top_level.txt
